{
  "taskid": "505f9fc483cf4df68a2409257b5fad7d3c58442",
  "backend": "mqtt",
  "brokers": [
    {
      "host": "localhost",
      "sort": "mqtt"
    },
    {
      "host": "localhost:10104",
      "sort": "p2p"
    }
  ],
  "groupAssociation": {
    "param-channel": "default"
  },
  "channels": [
    {
      "description": "Model update is sent from trainer to aggregator and vice-versa",
      "groupBy": {
        "type": "tag",
        "value": [
          "default"
        ]
      },
      "name": "param-channel",
      "pair": [
        "trainer",
        "aggregator"
      ],
      "funcTags": {
        "aggregator": [
          "distribute",
          "aggregate",
          "heartbeat_recv"
        ],
        "trainer": [
          "fetch",
          "upload",
          "heartbeat_send"
        ]
      }
    }
  ],
  "dataset": "https://storage.googleapis.com/tensorflow/tf-keras-datasets/mnist.npz",
  "dependencies": [
    "numpy >= 1.2.0"
  ],
  "hyperparameters": {
    "batchSize": 32,
    "learningRate": 0.04,
    "rounds": 5,
    "trainer_indices_list": [
      20815,
      9388,
      32910,
      17499,
      13211,
      42604,
      6313,
      10461,
      17937,
      7292,
      43735,
      31152,
      35440,
      45021,
      2119,
      24148,
      29066,
      22129,
      31217,
      32118,
      31444,
      29980,
      10262,
      12784,
      40226,
      8793,
      5329,
      28665,
      40397,
      24364,
      25061,
      31693,
      7491,
      32510,
      36670,
      43367,
      42338,
      38930,
      14655,
      2997,
      24085,
      43980,
      3621,
      40807,
      49770,
      46403,
      44975,
      4924,
      49676,
      3203,
      35865,
      21435,
      21672,
      43013,
      30134,
      44911,
      28324,
      48120,
      601,
      27950,
      43084,
      49118,
      22423,
      17553,
      45291,
      43316,
      23870,
      13008,
      38985,
      23266,
      28810,
      43527,
      147,
      17844,
      49627,
      6970,
      20725,
      42331,
      43505,
      32951,
      810,
      26210,
      25141,
      37904,
      46508,
      13004,
      47904,
      39819,
      12461,
      24498,
      406,
      37885,
      7728,
      32188,
      12498,
      6611,
      37572,
      23614,
      49022,
      24025,
      41525,
      22502,
      39377,
      23347,
      14225,
      49466,
      46662,
      23207,
      47504,
      17143,
      15663,
      19677,
      7964,
      24283,
      16599,
      47759,
      34950,
      42833,
      41850,
      32335,
      19368,
      16684,
      4665,
      32602,
      22533,
      22608,
      45766,
      39535,
      9584,
      4309,
      27078,
      22063,
      9396,
      44514,
      29595,
      23535,
      36554,
      13578,
      23822,
      6761,
      9917,
      21152,
      21599,
      27421,
      15979,
      282,
      221,
      49274,
      19832,
      36471,
      26839,
      42438,
      29225,
      36207,
      10186,
      33937,
      25762,
      13084,
      44831,
      43269,
      14110,
      12385,
      49285,
      44590,
      296,
      4467,
      35341,
      2090,
      39031,
      8573,
      28498,
      31917,
      4424,
      45619,
      18662,
      2322,
      4750,
      6863,
      8123,
      15331,
      5609,
      21606,
      38229,
      11390,
      22945,
      26337,
      45199,
      24116,
      44313,
      3753,
      8676,
      34075,
      7835,
      29056,
      17139,
      14244,
      3797,
      24903,
      3346,
      36664,
      13145,
      13190,
      13517,
      24730,
      30927,
      26357,
      10517,
      5632,
      5910,
      24316,
      23227,
      14518,
      46401,
      25123,
      7435,
      14056,
      24751,
      2283,
      12369,
      47399,
      5225,
      45837,
      18411,
      7427,
      29782,
      2011,
      42413,
      26012,
      36281,
      22175,
      24091,
      42918,
      20825,
      6593,
      11658,
      33411,
      28749,
      6270,
      20088,
      9045,
      34842,
      45357,
      36634,
      20206,
      35646,
      49457,
      12452,
      10102,
      38523,
      45293,
      32562,
      22857,
      28431,
      2396,
      28404,
      5059,
      27686,
      25922,
      21073,
      30835,
      5874,
      49010,
      10610,
      11445,
      13002,
      11933,
      17731,
      12098,
      35029,
      45981,
      12691,
      1600,
      11891,
      16004,
      428,
      18029,
      40868,
      16659,
      32271,
      7774,
      18355,
      49224,
      29362,
      43620,
      45280,
      32218,
      24172,
      17176,
      17870,
      2957,
      23050,
      31635,
      6656,
      9385,
      34409,
      18932,
      4105,
      17463,
      9756,
      39089,
      47329,
      5312,
      10758,
      46823,
      30417,
      40276,
      33564,
      10538,
      32553,
      5789,
      9109,
      25364,
      5371,
      16305,
      29944,
      49307,
      35605,
      49602,
      1649,
      16309,
      43933,
      43760,
      345,
      8385,
      6875,
      36424,
      2358,
      25274,
      27311,
      34477,
      19017,
      49619,
      26507,
      43618,
      42445,
      7899,
      7636,
      19900,
      16729,
      39044,
      16570,
      31073,
      47267,
      6089,
      28717,
      19710,
      31666,
      24239,
      15651,
      43420,
      35505,
      6425,
      4920,
      3240,
      33886,
      24675,
      24921,
      22500,
      10586,
      36333,
      5061,
      6933,
      23605,
      39038,
      35484,
      39006,
      40883,
      33437,
      31625,
      33419,
      47275,
      10697,
      3766,
      32342,
      6898,
      20809,
      47518,
      23734,
      10437,
      12797,
      11821,
      18803,
      42223,
      1502,
      46146,
      38358,
      4702,
      1092,
      40772,
      14304,
      16054,
      44096,
      4112,
      32315,
      35079,
      19515,
      5058,
      8677,
      45414,
      45365,
      43096,
      21522,
      35588,
      32112,
      11529,
      15655,
      6744,
      33276,
      46579,
      25411,
      8064,
      24118,
      6772,
      43169,
      26691,
      12255,
      44402,
      40057,
      24280,
      25661,
      37728,
      24593,
      23275,
      19549,
      17854,
      40843,
      19663,
      32198,
      13690,
      29725,
      476,
      19522,
      11985,
      36542,
      24160,
      23346,
      21573,
      14220,
      29472,
      45011,
      659,
      44840,
      16726,
      40901,
      8794,
      37104,
      5642,
      5458,
      22966,
      28239,
      5116,
      12332,
      26247,
      48895,
      35225,
      42070,
      24462,
      21292,
      10768,
      6720,
      38200,
      3129,
      43309,
      4343,
      23970,
      1050,
      11092,
      32825,
      35149,
      33024,
      14372,
      13127,
      5934,
      10505,
      26111,
      23191,
      11064,
      26514,
      48450,
      40125,
      18088,
      5922,
      8740,
      18207,
      20513,
      41725,
      3634,
      28232,
      6257,
      30566,
      42503,
      47238,
      49161,
      34284,
      30683,
      10728
    ],
    "failure_durations_s": "[(171, 583), (814, 504), (1356, 101), (1484, 269), (1983, 113), (2116, 298), (2434, 190), (2934, 479), (3416, 421), (3895, 26), (3934, 321), (4307, 452), (4786, 229), (5100, 300)]",
    "heartbeats": {
      "enabled": "False",
      "frequency_s": 1
    },
    "use_oort_loss_fn": "True",
    "client_avail_aware_notify": "True",
    "training_delay_enabled": "True",
    "training_delay_s": "6.0"
  },
  "baseModel": {
    "name": "",
    "version": 1
  },
  "job": {
    "id": "622a358619ab59012eabeefb",
    "name": "cifar-10"
  },
  "registry": {
    "sort": "dummy",
    "uri": ""
  },
  "selector": {
    "sort": "fedbuff",
    "kwargs": {
      "c": 20,
      "aggGoal": 1
    }
  },
  "optimizer": {
    "sort": "fedavg",
    "kwargs": {}
  },
  "maxRunTime": 300,
  "realm": "default/us",
  "role": "trainer"
}