{
  "taskid": "505f9fc483cf4df68a2409257b5fad7d3c580426",
  "backend": "mqtt",
  "brokers": [
    {
      "host": "130.207.125.87",
      "sort": "mqtt"
    },
    {
      "host": "localhost:10104",
      "sort": "p2p"
    }
  ],
  "groupAssociation": {
    "param-channel": "default"
  },
  "channels": [
    {
      "description": "Model update is sent from trainer to aggregator and vice-versa",
      "groupBy": {
        "type": "tag",
        "value": [
          "default"
        ]
      },
      "name": "param-channel",
      "pair": [
        "trainer",
        "aggregator"
      ],
      "funcTags": {
        "aggregator": [
          "distribute",
          "aggregate"
        ],
        "trainer": [
          "fetch",
          "upload"
        ]
      }
    }
  ],
  "dataset": "https://storage.googleapis.com/tensorflow/tf-keras-datasets/mnist.npz",
  "dependencies": [
    "numpy >= 1.2.0"
  ],
  "hyperparameters": {
    "batchSize": 32,
    "learningRate": 0.000195,
    "rounds": 5,
    "trainer_indices_list": [
      8173,
      9015,
      8450,
      9361,
      9044,
      8298,
      10482,
      10024,
      16095,
      14850,
      15694,
      15150,
      14280,
      19401,
      18924,
      19928,
      19525,
      19506,
      18936,
      19735,
      19199,
      18863,
      19914,
      19018,
      18939,
      19868,
      19367,
      19682,
      19386,
      19706,
      19699,
      19780,
      18823,
      19850,
      19656,
      18937,
      19580,
      19840,
      19502,
      19845,
      19585,
      18721,
      19937,
      18997,
      19803,
      19128,
      19124,
      18792,
      19786,
      19480,
      19100,
      18908,
      19766,
      19226,
      19189,
      19859,
      18732,
      18941,
      18873,
      19455,
      19910,
      19591,
      19550,
      19396,
      19666,
      19474,
      19601,
      19573,
      19111,
      19597,
      19805,
      19730,
      19347,
      19190,
      19486,
      19582,
      18926,
      19903,
      19638,
      19335,
      18748,
      19026,
      19746,
      19269,
      19325,
      19175,
      19060,
      19660,
      19429,
      19900,
      19167,
      18922,
      19556,
      19294,
      19208,
      19153,
      19059,
      19870,
      19547,
      18723,
      19630,
      18992,
      19527,
      19906,
      18940,
      23094,
      25823,
      23438,
      23186,
      25876,
      25222,
      25791,
      23381,
      24651,
      24071,
      23326,
      25983,
      25770,
      23009,
      24710,
      23008,
      25469,
      24043,
      22986,
      25577,
      25729,
      24903,
      25113,
      22936,
      23441,
      23252,
      25856,
      28934,
      28271,
      28194,
      27909,
      28318,
      29097,
      28980,
      28208,
      28255,
      28191,
      29128,
      28112,
      29233,
      28085,
      27933,
      29206,
      29111,
      28533,
      28480,
      28111,
      27817,
      28192,
      27715,
      27913,
      28140,
      28788,
      37784,
      37347,
      35579,
      36129,
      37629,
      36408,
      35752,
      35647,
      37068,
      37499,
      35396,
      38200,
      37381,
      36691,
      35621,
      36244,
      37693,
      36540,
      38097,
      36275,
      38253,
      38293,
      38517,
      38527,
      35963,
      37410,
      36127,
      37301,
      37484,
      35541,
      37357,
      38128,
      38466,
      37669,
      35914,
      36453,
      35419,
      38089,
      35569,
      36549,
      37061,
      35607,
      36038,
      36910,
      46735,
      47250,
      47738,
      47710,
      47662,
      46351,
      46058,
      45546,
      44792,
      46835,
      45765,
      45556,
      45063,
      47026,
      45123,
      44996,
      44743,
      45764,
      45647,
      45507,
      45173,
      45174,
      45878,
      45932,
      45417,
      46698,
      46537,
      45759,
      45883,
      47570,
      46879,
      47048,
      47172,
      44765,
      46329,
      46284,
      44869,
      45751,
      46661,
      47232,
      45111,
      45532,
      47333,
      45515,
      47194,
      45804,
      45261,
      45000,
      45166,
      47508,
      47511,
      46963,
      47697,
      47362,
      47408,
      46165,
      46176,
      46017,
      46186,
      45319,
      47239,
      45622,
      45663,
      46293,
      46125,
      47536,
      44919,
      47382,
      45782,
      44723,
      45747,
      47717,
      47052,
      44775,
      47257,
      45440,
      47062,
      46792,
      46213,
      45704,
      46312,
      44948,
      44674,
      44791,
      45717,
      45771,
      46390,
      46308,
      46420,
      44859,
      46567,
      47592,
      46246,
      49038,
      49107,
      53348,
      51290,
      51439,
      54899,
      54575,
      54467,
      55139,
      55220,
      55726,
      55033,
      55586,
      55296,
      55779,
      57058,
      55848,
      55061,
      55170,
      55180,
      56032,
      55839,
      54135,
      57014,
      57022,
      55843,
      56967,
      54177,
      56961,
      55546,
      56792,
      53969,
      54098,
      54066,
      54585,
      54676,
      54555,
      55555,
      54407,
      56970,
      57059,
      54902,
      55858,
      55168,
      56184,
      55714,
      54469,
      56825,
      55523,
      55209,
      54108,
      54592,
      54927,
      55109,
      55322,
      54918,
      54992,
      54384,
      55706,
      54282,
      54615,
      55083,
      56482,
      56968,
      55994,
      56653,
      56953,
      57298,
      57486,
      57212,
      57479,
      57576,
      58239,
      58001,
      58385,
      57358,
      57268,
      58360,
      57296,
      58175,
      58687,
      57668,
      57421,
      57599,
      58203,
      57678,
      58382,
      57615,
      58683,
      57705,
      58065,
      57172,
      58202,
      57786,
      71275,
      71172,
      70175,
      71052,
      71856,
      72084,
      71817,
      69934,
      72377,
      71507,
      69372,
      71547,
      71077,
      71723,
      71647,
      72115,
      70870,
      72668,
      72994,
      73469,
      73863,
      72456,
      72706
    ],
    "failure_durations_s": "[(4, 1600), (6918, 6443), (14665, 4058), (19393, 2027), (21899, 59), (21997, 1338), (31381, 1), (33041, 10903), (46817, 4177), (51712, 143), (52189, 9282), (61779, 7), (63295, 9278), (74611, 4380), (79350, 21474), (102204, 193), (103472, 4606), (108511, 44), (109121, 11472), (121838, 8883), (131790, 1302), (133963, 3920), (138618, 10630), (149914, 10013), (161334, 3590)]",
    "heartbeats": {
      "enabled": "False",
      "frequency_s": 1
    },
    "use_oort_loss_fn": "False",
    "client_avail_aware_notify": "True",
    "training_delay_enabled": "True",
    "training_delay_s": "30.0"
  },
  "baseModel": {
    "name": "",
    "version": 1
  },
  "job": {
    "id": "622a358619ab59012eabeefb",
    "name": "cifar-10"
  },
  "registry": {
    "sort": "dummy",
    "uri": ""
  },
  "selector": {
    "sort": "fedbuff",
    "kwargs": {
      "c": 20,
      "aggGoal": 1
    }
  },
  "optimizer": {
    "sort": "fedavg",
    "kwargs": {}
  },
  "maxRunTime": 300,
  "realm": "default/us",
  "role": "trainer"
}