{
  "taskid": "505f9fc483cf4df68a2409257b5fad7d3c580408",
  "backend": "mqtt",
  "brokers": [
    {
      "host": "localhost",
      "sort": "mqtt"
    },
    {
      "host": "localhost:10104",
      "sort": "p2p"
    }
  ],
  "groupAssociation": {
    "param-channel": "default"
  },
  "channels": [
    {
      "description": "Model update is sent from trainer to aggregator and vice-versa",
      "groupBy": {
        "type": "tag",
        "value": [
          "default"
        ]
      },
      "name": "param-channel",
      "pair": [
        "trainer",
        "aggregator"
      ],
      "funcTags": {
        "aggregator": [
          "distribute",
          "aggregate"
        ],
        "trainer": [
          "fetch",
          "upload"
        ]
      }
    }
  ],
  "dataset": "https://storage.googleapis.com/tensorflow/tf-keras-datasets/mnist.npz",
  "dependencies": [
    "numpy >= 1.2.0"
  ],
  "hyperparameters": {
    "batchSize": 32,
    "learningRate": 0.04,
    "rounds": 5,
    "trainer_indices_list": [
      778,
      197,
      937,
      714,
      861,
      406,
      342,
      853,
      963,
      1169,
      5,
      115,
      1069,
      825,
      13,
      711,
      1744,
      1630,
      2010,
      2241,
      2605,
      2288,
      1762,
      2553,
      4466,
      3656,
      3617,
      3311,
      4628,
      3815,
      3066,
      3857,
      4490,
      3678,
      3812,
      4096,
      3527,
      3786,
      3047,
      4409,
      3733,
      5004,
      5690,
      4683,
      5692,
      5362,
      5296,
      4715,
      5862,
      5183,
      5664,
      5478,
      5106,
      6232,
      5640,
      5098,
      5179,
      5200,
      7191,
      7293,
      7782,
      6817,
      7299,
      7136,
      7312,
      6463,
      6729,
      6451,
      7018,
      6881,
      9640,
      9252,
      11041,
      8009,
      10752,
      8369,
      10055,
      8761,
      9887,
      8559,
      10838,
      9649,
      8925,
      10593,
      8687,
      8620,
      10066,
      9194,
      10693,
      10750,
      9741,
      10403,
      8541,
      10696,
      9461,
      10906,
      9445,
      9347,
      9530,
      9007,
      10112,
      10303,
      9066,
      10629,
      11113,
      8183,
      9536,
      8105,
      10241,
      10074,
      11792,
      13594,
      12592,
      12611,
      12907,
      11300,
      12841,
      12637,
      11482,
      11600,
      13373,
      12141,
      11578,
      11180,
      11808,
      12508,
      14031,
      11704,
      11246,
      12800,
      13486,
      13673,
      13439,
      13042,
      13065,
      11946,
      12075,
      13461,
      12946,
      13051,
      11834,
      11563,
      14015,
      13875,
      12038,
      12992,
      13774,
      11536,
      13660,
      13987,
      15095,
      15565,
      15798,
      15796,
      16907,
      16538,
      15366,
      17112,
      14226,
      17116,
      15269,
      15418,
      16612,
      14825,
      17150,
      17141,
      15682,
      16161,
      16402,
      17005,
      16274,
      17137,
      15959,
      17609,
      18433,
      18398,
      17923,
      18633,
      18311,
      18083,
      17565,
      18483,
      18464,
      18405,
      17647,
      18638,
      18652,
      17523,
      19592,
      19064,
      19860,
      18873,
      19815,
      19669,
      19044,
      19287,
      18837,
      19226,
      18823,
      19159,
      19806,
      20984,
      21783,
      20160,
      21369,
      22019,
      20878,
      20867,
      21058,
      21278,
      21371,
      21985,
      21697,
      20690,
      21458,
      21048,
      20820,
      21512,
      22135,
      24894,
      25378,
      25472,
      24079,
      25827,
      22945,
      24616,
      23092,
      25589,
      22972,
      25705,
      23746,
      25177,
      23275,
      23971,
      23556,
      24396,
      25262,
      24584,
      25820,
      25398,
      25577,
      25106,
      27342,
      27088,
      26579,
      27118,
      27317,
      27545,
      26295,
      27191,
      27302,
      27268,
      26253,
      27124,
      26336,
      26073,
      29007,
      28351,
      27804,
      29060,
      28984,
      28435,
      27672,
      28773,
      28337,
      28883,
      29185,
      27833,
      28885,
      28486,
      28959,
      29165,
      29219,
      28296,
      27988,
      29235,
      27915,
      27917,
      30451,
      30004,
      30074,
      30336,
      29646,
      30562,
      30305,
      30457,
      29751,
      30525,
      30179,
      29724,
      29976,
      30493,
      29700,
      30590,
      29585,
      33439,
      31666,
      31178,
      31839,
      31174,
      32629,
      31134,
      33556,
      33090,
      32904,
      31283,
      32288,
      31455,
      31715,
      31724,
      31548,
      33188,
      32784,
      31781,
      31256,
      33402,
      31340,
      34518,
      35339,
      34025,
      33970,
      35038,
      34758,
      34641,
      34604,
      35009,
      34296,
      36400,
      36596,
      36016,
      35682,
      38199,
      37997,
      36117,
      36687,
      37086,
      36800,
      35684,
      36560,
      38352,
      36766,
      36383,
      38373,
      38317,
      37414,
      37500,
      36642,
      36003,
      38040,
      36107,
      38086,
      37435,
      36515,
      36763,
      37693,
      37520,
      35993,
      40540,
      41515,
      39399,
      40329,
      39463,
      41309,
      40823,
      40381,
      39661,
      40833,
      41143,
      39160,
      41614,
      39787,
      39441,
      40859,
      40627,
      39298,
      40215,
      39658,
      38953,
      41446,
      40430,
      38920,
      43897,
      44059,
      44182,
      42064,
      42748,
      41833,
      43189,
      42063,
      43002,
      44231,
      43870,
      43805,
      42571,
      43090,
      42980,
      42770,
      44318,
      41737,
      42832,
      46952,
      46029,
      45434,
      46839,
      47110,
      45227,
      44862,
      44740,
      46056,
      47539,
      46720,
      47482,
      44826,
      46593,
      44793,
      45106,
      47403,
      44723,
      45543,
      47471,
      47666,
      47017,
      46757,
      44897,
      47015,
      45089,
      45617,
      45194,
      47692,
      45894,
      46897,
      45737,
      46159,
      44827,
      47461,
      45478,
      46653,
      47890,
      50767,
      48242,
      50471,
      49512,
      50479,
      50886,
      48841,
      50340,
      50688,
      48061,
      48173,
      50812,
      49947,
      47954,
      48116,
      48648,
      49900,
      50823,
      50487,
      50824,
      49715,
      48914,
      49989,
      50529,
      53217,
      52265,
      51259,
      52499,
      53664,
      53461,
      50904,
      51184,
      51472,
      52909,
      52890,
      53209,
      51629,
      51087,
      53724,
      51698,
      53764,
      51923,
      51922,
      51114,
      50928,
      51518,
      51247,
      55225,
      56140,
      56448,
      55868,
      55030,
      56904,
      56683,
      55260,
      56382,
      56239,
      54346,
      54679,
      56360,
      56630,
      56372,
      58380,
      57309,
      57637,
      57472,
      57848,
      57554,
      57467,
      58697,
      58706,
      57820,
      58285,
      57273,
      61530,
      59616,
      58839,
      61509,
      58762,
      59103,
      60567,
      60341,
      59001,
      61596,
      60446,
      60586,
      59686,
      59160,
      60159,
      59373,
      60244,
      59396,
      61720,
      61702,
      61188,
      59388,
      59172,
      58889,
      60085,
      60535,
      59361,
      58950,
      61411,
      60081,
      61141,
      61913,
      63198,
      63445,
      62929,
      64186,
      62694,
      63394,
      61897,
      62701,
      63079,
      67487,
      67318,
      65253,
      66296,
      65256,
      67440,
      66852,
      64940,
      65202,
      66741,
      66391,
      65068,
      67051,
      65902,
      65149,
      65493,
      65541,
      65396,
      67097,
      66267,
      69061,
      68219,
      68557,
      69281,
      67986,
      68991,
      68757,
      68006,
      68809,
      67908,
      67952,
      69013,
      69279,
      68806,
      70505,
      70479,
      70635,
      72382,
      71278,
      70246,
      71228,
      71972,
      71637,
      69507,
      70935,
      70059,
      72345,
      70811,
      71464,
      70031,
      70426,
      71752,
      70780,
      70388,
      70775,
      69647,
      70749,
      69550,
      71372,
      72150,
      70350,
      71103,
      70881,
      70460,
      69597,
      70746,
      71506,
      70698,
      70525,
      69842,
      71887,
      74422,
      74293,
      73618,
      73331,
      73037,
      74518,
      75037,
      73487,
      73016,
      73129,
      72811,
      73727,
      73149,
      74316,
      73098,
      74171,
      73234,
      74035,
      74132,
      73945,
      74450,
      72465,
      74850,
      75132,
      75004,
      72912,
      74953,
      74329,
      73669,
      74208,
      75309,
      74356,
      72636,
      74101,
      76286,
      76525,
      75524,
      75448,
      75766,
      76024,
      76571,
      75922,
      75989,
      75385,
      75852,
      75774,
      76034,
      75635,
      77211,
      78052,
      77764,
      77920,
      78077,
      77284,
      78064,
      76744,
      78082,
      76819,
      78087,
      77231,
      77814,
      76666,
      78261,
      77388,
      77529,
      76842,
      77151,
      78185,
      76818,
      77868,
      77896,
      77775,
      79800,
      80195,
      78872,
      81398,
      80402,
      79188,
      79514,
      78559,
      80496,
      79913,
      80667,
      79109,
      80763,
      80066,
      78540,
      80201,
      79878,
      80920,
      81204,
      80925,
      79460,
      79783,
      79748,
      78440,
      81245,
      84820,
      83979,
      81894,
      84484,
      84615,
      83882,
      83199,
      82647,
      82441,
      83681,
      83414,
      82798,
      84284,
      84452,
      83929,
      82131,
      82147,
      81868,
      82057,
      83244,
      82284,
      83941,
      82770,
      83389,
      84138,
      83504,
      84641,
      82463,
      83359,
      83818,
      83825,
      82101,
      83741,
      84399,
      82745,
      83964,
      84741,
      81783,
      84416
    ],
    "failure_durations_s": "[(21, 20166), (29146, 7142), (37530, 2425), (39956, 669), (41048, 1442), (42772, 4291), (47174, 16021), (64358, 43250), (108626, 23324), (133244, 7510), (141760, 23164)]",
    "heartbeats": {
      "enabled": "False",
      "frequency_s": 1
    },
    "use_oort_loss_fn": "True",
    "client_avail_aware_notify": "True",
    "training_delay_enabled": "True",
    "training_delay_s": "18.0"
  },
  "baseModel": {
    "name": "",
    "version": 1
  },
  "job": {
    "id": "622a358619ab59012eabeefb",
    "name": "cifar-10"
  },
  "registry": {
    "sort": "dummy",
    "uri": ""
  },
  "selector": {
    "sort": "fedbuff",
    "kwargs": {
      "c": 20,
      "aggGoal": 1
    }
  },
  "optimizer": {
    "sort": "fedavg",
    "kwargs": {}
  },
  "maxRunTime": 300,
  "realm": "default/us",
  "role": "trainer"
}