{
    "taskid": "505f9fc483cf4df68a2409257b5fad7d3c580425",
    "backend": "mqtt",
    "brokers": [
        {
            "host": "localhost",
            "sort": "mqtt"
        },
        {
            "host": "localhost:10104",
            "sort": "p2p"
        }
    ],
    "groupAssociation": {
        "param-channel": "default"
    },
    "channels": [
        {
            "description": "Model update is sent from trainer to aggregator and vice-versa",
            "groupBy": {
                "type": "tag",
                "value": [
                    "default"
                ]
            },
            "name": "param-channel",
            "pair": [
                "trainer",
                "aggregator"
            ],
            "funcTags": {
                "aggregator": [
                    "distribute",
                    "aggregate"
                ],
                "trainer": [
                    "fetch",
                    "upload"
                ]
            }
        }
    ],
    "dataset": "https://storage.googleapis.com/tensorflow/tf-keras-datasets/mnist.npz",
    "dependencies": [
        "numpy >= 1.2.0"
    ],
    "hyperparameters": {
        "batchSize": 32,
        "learningRate": 0.04,
        "rounds": 5,
        "trainer_indices_list": [
            7538,
            48904,
            20935,
            21509,
            32694,
            43481,
            25155,
            48203,
            20021,
            30128,
            25560,
            39721,
            36549,
            2676,
            41166,
            6692,
            37392,
            1437,
            9541,
            46305,
            33520,
            14562,
            4436,
            8992,
            45840,
            2551,
            768,
            14053,
            17393,
            29985,
            3381,
            23990,
            20653,
            14072,
            17367,
            42263,
            41541,
            20024,
            40699,
            30118,
            8650,
            32179,
            12124,
            22318,
            4987,
            20823,
            27624,
            23420,
            36327,
            48824,
            40642,
            29183,
            6281,
            15339,
            29125,
            32901,
            6344,
            44863,
            27519,
            35344,
            47109,
            42065,
            20353,
            7173,
            22365,
            48898,
            9744,
            35863,
            31897,
            38049,
            20579,
            13114,
            48790,
            32274,
            35400,
            10140,
            25068,
            16633,
            12864,
            12888,
            8624,
            6255,
            37266,
            948,
            32638,
            34915,
            4779,
            47615,
            31981,
            24435,
            31497,
            44973,
            17530,
            16366,
            19025,
            40007,
            43411,
            30754,
            7734,
            43978,
            3591,
            32715,
            37809,
            12377,
            40624,
            6557,
            24667,
            9485,
            19782,
            42541,
            1568,
            18582,
            7049,
            3385,
            10177,
            30219,
            15202,
            17369,
            19187,
            17195,
            30606,
            8224,
            38066,
            21299,
            9865,
            22994,
            29096,
            16805,
            40370,
            32825,
            30059,
            19201,
            19022,
            34879,
            43011,
            38165,
            31892,
            13473,
            46338,
            21488,
            23659,
            33780,
            45886,
            7299,
            18808,
            16169,
            49164,
            36325,
            4653,
            6308,
            28449,
            8702,
            12344,
            5481,
            40876,
            18545,
            41863,
            32194,
            26488,
            14488,
            37978,
            34190,
            6650,
            26662,
            5604,
            45349,
            10911,
            20473,
            35544,
            46922,
            23808,
            39519,
            15992,
            33117,
            7311,
            46019,
            21974,
            1999,
            11812,
            31837,
            49420,
            43303,
            47677,
            22692,
            45936,
            17764,
            28765,
            31961,
            1338
        ],
        "heartbeats": {
            "enabled": "False",
            "frequency_s": 1
        },
        "use_oort_loss_fn": "True",
        "training_delay_enabled": "True",
        "training_delay_s": "23.0",
        "avl_events_3_state_50": "[(0, 'AVL_TRAIN'), (300, 'AVL_EVAL'), (3785, 'UN_AVL'), (67339, 'AVL_TRAIN'), (70372, 'UN_AVL'), (90088, 'AVL_TRAIN'), (105890, 'AVL_EVAL'), (211817, 'UN_AVL'), (323903, 'AVL_EVAL'), (352242, 'UN_AVL'), (380055, 'AVL_TRAIN'), (387626, 'AVL_EVAL'), (389230, 'AVL_TRAIN'), (395929, 'AVL_EVAL'), (432844, 'UN_AVL'), (468462, 'AVL_TRAIN'), (473226, 'AVL_EVAL'), (477430, 'UN_AVL')]",
        "avl_events_3_state_75": "[(0, 'AVL_TRAIN'), (300, 'UN_AVL'), (67339, 'AVL_TRAIN'), (70372, 'UN_AVL'), (90088, 'AVL_TRAIN'), (105890, 'AVL_EVAL'), (163572, 'UN_AVL'), (323903, 'AVL_EVAL'), (334910, 'UN_AVL'), (380055, 'AVL_TRAIN'), (387626, 'AVL_EVAL'), (389230, 'AVL_TRAIN'), (395929, 'AVL_EVAL'), (425206, 'UN_AVL'), (468462, 'AVL_TRAIN'), (473226, 'UN_AVL')]",
        "avl_events_2_state": "[(0, 'AVL_TRAIN'), (300, 'UN_AVL'), (67339, 'AVL_TRAIN'), (70372, 'UN_AVL'), (90088, 'AVL_TRAIN'), (105890, 'UN_AVL'), (380055, 'AVL_TRAIN'), (387626, 'UN_AVL'), (389230, 'AVL_TRAIN'), (395929, 'UN_AVL'), (468462, 'AVL_TRAIN'), (473226, 'UN_AVL')]",
        "client_notify": {
            "enabled": "False",
            "type": "three_state"
        },
        "wait_until_next_avl": "True",
        "avl_events_syn_0": "[(0, 'AVL_TRAIN')]",
        "avl_events_syn_20": "[(0, 'AVL_TRAIN'), (6600, 'UN_AVL'), (7200, 'AVL_TRAIN'), (20400, 'UN_AVL'), (21000, 'AVL_TRAIN'), (22800, 'UN_AVL'), (23400, 'AVL_TRAIN'), (43200, 'UN_AVL'), (43800, 'AVL_TRAIN'), (44400, 'UN_AVL'), (45000, 'AVL_TRAIN'), (54000, 'UN_AVL'), (54600, 'AVL_TRAIN'), (55200, 'UN_AVL'), (55800, 'AVL_TRAIN'), (62400, 'UN_AVL'), (63000, 'AVL_TRAIN'), (63600, 'UN_AVL'), (64200, 'AVL_TRAIN'), (64800, 'UN_AVL'), (66000, 'AVL_TRAIN'), (86400, 'UN_AVL')]",
        "avl_events_syn_40": "[(0, 'AVL_TRAIN'), (86400, 'UN_AVL')]"
    },
    "baseModel": {
        "name": "",
        "version": 1
    },
    "job": {
        "id": "622a358619ab59012eabeefb",
        "name": "cifar-10"
    },
    "registry": {
        "sort": "dummy",
        "uri": ""
    },
    "selector": {
        "sort": "fedbuff",
        "kwargs": {
            "c": 20,
            "aggGoal": 1
        }
    },
    "optimizer": {
        "sort": "fedavg",
        "kwargs": {}
    },
    "maxRunTime": 300,
    "realm": "default/us",
    "role": "trainer"
}