{
    "taskid": "505f9fc483cf4df68a2409257b5fad7d3c580603",
    "backend": "mqtt",
    "brokers": [
        {
            "host": "130.207.125.87",
            "sort": "mqtt"
        },
        {
            "host": "localhost:10104",
            "sort": "p2p"
        }
    ],
    "groupAssociation": {
        "param-channel": "default"
    },
    "channels": [
        {
            "description": "Model update is sent from trainer to aggregator and vice-versa",
            "groupBy": {
                "type": "tag",
                "value": [
                    "default"
                ]
            },
            "name": "param-channel",
            "pair": [
                "trainer",
                "aggregator"
            ],
            "funcTags": {
                "aggregator": [
                    "distribute",
                    "aggregate"
                ],
                "trainer": [
                    "fetch",
                    "upload"
                ]
            }
        }
    ],
    "dataset": "https://storage.googleapis.com/tensorflow/tf-keras-datasets/mnist.npz",
    "dependencies": [
        "numpy >= 1.2.0"
    ],
    "hyperparameters": {
        "batchSize": 32,
        "learningRate": 0.04,
        "rounds": 5,
        "trainer_indices_list": [
            714,
            1214,
            484,
            381,
            2744,
            2838,
            2589,
            1629,
            2804,
            4496,
            3454,
            4413,
            4202,
            4186,
            6155,
            4853,
            5515,
            6211,
            5581,
            6231,
            7314,
            7005,
            7087,
            6371,
            6822,
            11072,
            10907,
            10306,
            9294,
            8981,
            9615,
            9814,
            8660,
            10868,
            13610,
            11679,
            12836,
            13618,
            12969,
            12207,
            12884,
            14004,
            16648,
            15843,
            14834,
            14672,
            16567,
            16327,
            14183,
            15321,
            14345,
            14233,
            14771,
            18572,
            17817,
            18257,
            19489,
            19520,
            19704,
            18822,
            22637,
            21234,
            22712,
            20573,
            22609,
            21196,
            20309,
            20788,
            22501,
            20451,
            23450,
            25868,
            23308,
            26002,
            23535,
            24732,
            25011,
            24035,
            24332,
            24921,
            25116,
            27374,
            27390,
            26931,
            27594,
            27943,
            27897,
            28476,
            29181,
            27961,
            29365,
            30532,
            30630,
            30487,
            33055,
            31209,
            31142,
            33187,
            32852,
            30748,
            33219,
            33644,
            33053,
            33728,
            34144,
            34862,
            35065,
            34585,
            35206,
            36395,
            37297,
            36856,
            36406,
            37280,
            35435,
            37028,
            38089,
            38072,
            37488,
            39681,
            40128,
            39357,
            39948,
            39363,
            38931,
            40820,
            40029,
            40117,
            40340,
            39781,
            44017,
            42496,
            44172,
            44440,
            42901,
            44551,
            41883,
            43874,
            45186,
            45604,
            46948,
            47521,
            45090,
            46355,
            46170,
            46050,
            50037,
            47833,
            49277,
            50745,
            49964,
            49876,
            49037,
            50102,
            48126,
            48303,
            50413,
            50336,
            53681,
            52858,
            52262,
            52499,
            51804,
            51536,
            53700,
            51152,
            53447,
            56425,
            54008,
            55602,
            54114,
            57084,
            54212,
            53979,
            56930,
            56460,
            55537,
            57727,
            57989,
            57935,
            57136,
            58507,
            61261,
            59316,
            59421,
            59512,
            61301,
            60781,
            60005,
            61623,
            59106,
            60841,
            61944,
            63171,
            63901,
            64622,
            63714,
            63547,
            63310,
            63048,
            63899,
            62053,
            67585,
            66229,
            67330,
            66789,
            67122,
            66364,
            64959,
            66815,
            66332,
            66481,
            68540,
            68327,
            69175,
            68201,
            72111,
            70117,
            70989,
            70542,
            71231,
            71837,
            71895,
            71889,
            71134,
            71260,
            73263,
            73561,
            72563,
            74543,
            73516,
            73289,
            73796,
            73480,
            74877,
            75895,
            75835,
            76552,
            75818,
            77018,
            78307,
            76824,
            77085,
            78035,
            81044,
            79562,
            80421,
            79072,
            80790,
            81233,
            80951,
            78774,
            80102,
            82720,
            83196,
            82706,
            81911,
            84047,
            82788,
            82096,
            84161,
            82153,
            81978
        ],
        "failure_durations_s": "[(25, 80), (250, 479), (764, 29), (960, 73), (2575, 2615), (6248, 7518), (13894, 76), (15079, 2695), (19637, 1963)]",
        "heartbeats": {
            "enabled": "False",
            "frequency_s": 1
        },
        "use_oort_loss_fn": "True",
        "client_avail_aware_notify": "True",
        "training_delay_enabled": "True",
        "training_delay_s": "1.0"
    },
    "baseModel": {
        "name": "",
        "version": 1
    },
    "job": {
        "id": "622a358619ab59012eabeefb",
        "name": "cifar-10"
    },
    "registry": {
        "sort": "dummy",
        "uri": ""
    },
    "selector": {
        "sort": "fedbuff",
        "kwargs": {
            "c": 20,
            "aggGoal": 1
        }
    },
    "optimizer": {
        "sort": "fedavg",
        "kwargs": {}
    },
    "maxRunTime": 300,
    "realm": "default/us",
    "role": "trainer"
}