{
    "taskid": "505f9fc483cf4df68a2409257b5fad7d3c580441",
    "backend": "mqtt",
    "brokers": [
        {
            "host": "localhost",
            "sort": "mqtt"
        },
        {
            "host": "localhost:10104",
            "sort": "p2p"
        }
    ],
    "groupAssociation": {
        "param-channel": "default"
    },
    "channels": [
        {
            "description": "Model update is sent from trainer to aggregator and vice-versa",
            "groupBy": {
                "type": "tag",
                "value": [
                    "default"
                ]
            },
            "name": "param-channel",
            "pair": [
                "trainer",
                "aggregator"
            ],
            "funcTags": {
                "aggregator": [
                    "distribute",
                    "aggregate"
                ],
                "trainer": [
                    "fetch",
                    "upload"
                ]
            }
        }
    ],
    "dataset": "https://storage.googleapis.com/tensorflow/tf-keras-datasets/mnist.npz",
    "dependencies": [
        "numpy >= 1.2.0"
    ],
    "hyperparameters": {
        "batchSize": 32,
        "learningRate": 0.000195,
        "rounds": 5,
        "trainer_indices_list": [
            21605,
            32034,
            2820,
            42517,
            42701,
            31996,
            34254,
            15483,
            13808,
            6190,
            27919,
            18378,
            35524,
            38431,
            15676,
            4046,
            9493,
            49344,
            16159,
            17010,
            34018,
            46445,
            28703,
            45461,
            11642,
            18624,
            31955,
            6648,
            16860,
            15346,
            21227,
            1699,
            32602,
            41048,
            6247,
            18548,
            28618,
            27699,
            15716,
            17890,
            6166,
            1417,
            859,
            37377,
            29446,
            4841,
            30745,
            13714,
            21840,
            10974,
            33992,
            5348,
            36427,
            6775,
            36783,
            4597,
            46807,
            8355,
            35679,
            32207,
            4757,
            27552,
            20711,
            35274,
            17418,
            49180,
            21665,
            21383,
            47758,
            11529,
            28507,
            11576,
            34656,
            4066,
            10475,
            14207,
            14804,
            44691,
            5341,
            47373,
            31625,
            16954,
            26454,
            47119,
            49182,
            34963,
            33356,
            20598,
            26488,
            36287,
            48457,
            2160,
            22579,
            10702,
            30770,
            10434,
            39193,
            10317,
            40019,
            17592,
            10444,
            6346,
            42203,
            2643,
            608,
            43872,
            30591,
            28270,
            19314,
            48217,
            24093,
            7965,
            40001,
            38524,
            9351,
            49967,
            35078,
            42202,
            34198,
            5752,
            45777,
            9387,
            40683,
            37329,
            32037,
            32290,
            41950,
            16414,
            26306,
            48342,
            34576,
            1080,
            26879,
            46926,
            39999,
            42400,
            17874,
            41250,
            42254,
            44156,
            45262,
            5378,
            46015,
            34100,
            39571,
            31289,
            26312,
            843,
            40470,
            3765,
            8494,
            46249,
            14442,
            44333,
            2006,
            37808,
            42674,
            36802,
            49746,
            46975,
            6478,
            5482,
            32619,
            49235,
            6565,
            31929,
            4971,
            8180,
            41835,
            23355,
            21635,
            37144,
            31066,
            24488,
            10682,
            20045,
            459,
            38320,
            49852,
            16624,
            45037,
            27612,
            5089,
            5483,
            35160,
            4892,
            46675,
            3950,
            23793,
            1508,
            1960,
            35912,
            43400,
            31001,
            1996,
            49245,
            41957,
            33783,
            39350,
            38460,
            43184,
            31581,
            34523,
            45161,
            40679,
            42288,
            46210,
            28599,
            31015,
            26300,
            10003,
            2778,
            9366,
            40614,
            30299,
            23757,
            21681,
            26341,
            4923,
            34799,
            3707,
            25756,
            18220,
            12481,
            21901,
            27686,
            7046,
            48911,
            44594,
            25042,
            2277,
            10708,
            29500,
            35562,
            5457,
            27449,
            40179,
            958,
            44685,
            48347,
            18234,
            9844,
            28687,
            43794,
            34342,
            38348,
            40376,
            8111,
            13951,
            12490,
            36391,
            3024,
            48459,
            30444,
            44303,
            33372,
            27378,
            47265,
            30664,
            2523,
            18105,
            7169,
            45185,
            18231,
            46113,
            26815,
            36108,
            6541,
            42002,
            49752,
            30601,
            11554,
            37722,
            13197,
            39864,
            43101,
            25580,
            14389,
            43485,
            24020,
            46749,
            1370,
            21710,
            28940,
            21457,
            38332,
            25225,
            16305,
            30277,
            3094,
            28548,
            22410,
            598,
            42571,
            6956,
            18933,
            37641,
            44031,
            17133,
            44599,
            5360,
            36119,
            43096,
            29175,
            7045,
            42952,
            39627,
            16721,
            23117,
            41941,
            3967,
            16558,
            20419,
            20822,
            19587,
            6143,
            32573,
            49236,
            9596,
            1289,
            40287,
            12951,
            14891,
            9390,
            8048,
            5185,
            7507,
            4281,
            43086,
            49525,
            2368,
            17696,
            29479,
            18382,
            37659,
            48550,
            45067,
            37362,
            16186,
            18368,
            9344,
            30577,
            22401,
            6328,
            41507,
            34949,
            41880,
            29678,
            49532,
            48871,
            28985,
            34009,
            17149,
            28016,
            2640,
            20662,
            1261,
            10620,
            46387,
            15955,
            13489,
            30636,
            41744,
            20471,
            47842,
            33554,
            22496,
            35039,
            23201,
            39059,
            30652,
            11566,
            20479,
            11013,
            1720,
            18991,
            37355,
            26381,
            14028,
            21856,
            14456,
            19090,
            36722,
            29929,
            21596,
            7013,
            40122,
            30376,
            43212,
            29826,
            29782,
            39670,
            33449,
            37797,
            1183,
            26703,
            24578,
            8057,
            22114,
            23109,
            6312,
            40524,
            36229,
            33104,
            26666,
            8283,
            9966,
            20936,
            31249,
            46735,
            7643,
            2434,
            106,
            46313,
            24451,
            25470,
            2534,
            24251,
            49510,
            41882,
            18275,
            10716,
            27571,
            30515,
            22492,
            26580,
            3626,
            22948,
            8961,
            37558,
            1665,
            31317,
            25924,
            38536,
            1732,
            23480,
            13743,
            9220,
            16116,
            35505,
            47393,
            6313,
            49968,
            18367,
            30294,
            22649,
            23371,
            7934,
            28401,
            826,
            32014,
            3319,
            19928,
            10805,
            6004,
            43705,
            19149,
            20161,
            1036,
            15490,
            49149,
            48372,
            35179,
            35374,
            3860,
            7413,
            26437,
            16466,
            24127,
            46363,
            4432,
            26898,
            22551,
            25192,
            9614,
            10923,
            46248,
            26225,
            9306,
            3857,
            13735,
            6242,
            33145,
            42151,
            38264,
            11593,
            7535,
            19748,
            46854,
            25472,
            33817,
            49876,
            29882,
            22581,
            15077,
            25902,
            9057,
            30874,
            11216,
            49220,
            32716,
            26334,
            35282,
            1292,
            38053,
            13788,
            18266,
            43149,
            16071,
            49899,
            10142,
            32727,
            40669,
            16330,
            17271,
            38540,
            40018,
            30076,
            8715,
            25717,
            44414,
            38339,
            12426,
            26603,
            24990,
            25066,
            3347,
            32411,
            308,
            48311,
            22504,
            3670,
            10286,
            8163,
            26156,
            8211,
            8006,
            43076,
            39613,
            17188,
            23384,
            29051,
            28972,
            25054,
            7409,
            29336,
            22760,
            48856,
            20358,
            21924,
            43849,
            41714,
            19991,
            41434,
            62,
            9545,
            10689,
            49677,
            40485,
            7443,
            32016,
            27532,
            13348,
            23855,
            25501,
            33617,
            39198,
            36295,
            3168,
            28052,
            36733,
            24984,
            37437,
            12286,
            23707,
            23845,
            38817,
            45243,
            17004,
            26038,
            26761,
            40939,
            39787,
            12172,
            9651,
            3681,
            10411,
            26109,
            18900,
            19318,
            38917,
            46464,
            29762,
            3170,
            27543,
            5852,
            25238,
            7537,
            23838,
            48225,
            26487,
            26720,
            3113,
            28897,
            2658,
            30018,
            49308,
            26170,
            4594,
            27618,
            48936,
            19339,
            43381,
            42207,
            18616,
            23214,
            29134,
            15276,
            42325,
            10848,
            20395,
            31903,
            40332,
            11977,
            5623,
            5643,
            12418,
            44569,
            909,
            14866,
            34089,
            28641,
            27839,
            1480,
            19696,
            3269,
            16511,
            20491,
            3250,
            25808,
            24589,
            16015,
            49393,
            8455,
            17178,
            7347,
            26608,
            44170,
            29544,
            276,
            40458,
            14497,
            35725,
            13406,
            35999,
            4543,
            27640,
            27886,
            3121,
            29476,
            49631,
            28841,
            10986,
            34491,
            36876,
            27056,
            46142,
            42301,
            28128,
            47401,
            14991,
            8922,
            46584,
            18795,
            40223,
            48872,
            25653,
            45327,
            6459,
            31888,
            1185,
            39704,
            44477,
            37858,
            32618,
            9684,
            42972,
            27337,
            21646,
            18125,
            23080,
            9972,
            31369,
            21579,
            38608,
            43805,
            26004,
            35973,
            25395,
            45985,
            4051,
            44759,
            20604,
            11682,
            10856,
            2646,
            40983,
            29856,
            40137,
            34030,
            18075,
            4972,
            27978,
            23581,
            35621,
            46057,
            6646,
            14821,
            43674,
            21342,
            41253,
            38586,
            36966,
            35345,
            42829,
            37432,
            15893,
            475,
            4233,
            38567,
            31119,
            34094,
            49415,
            10402,
            15928,
            4778,
            13641,
            22064,
            25316,
            32718,
            38589,
            46012,
            15473,
            46706,
            47658,
            41122,
            42926,
            8425,
            8401,
            34104,
            49161,
            8026,
            1058,
            3375,
            36746,
            39502,
            37565,
            29444,
            30035,
            13238,
            3906,
            36024,
            43288,
            49410,
            42572,
            20081,
            21312,
            31392,
            46922,
            45784,
            34315,
            40796,
            40913,
            36390,
            11277,
            30071,
            22696,
            34577,
            32200,
            11616,
            48618,
            39675,
            4780,
            29333,
            18831,
            7183,
            25093,
            49346
        ],
        "failure_durations_s": "[]"
    },
    "baseModel": {
        "name": "",
        "version": 1
    },
    "job": {
        "id": "622a358619ab59012eabeefb",
        "name": "cifar-10"
    },
    "registry": {
        "sort": "dummy",
        "uri": ""
    },
    "selector": {
        "sort": "default",
        "kwargs": {}
    },
    "optimizer": {
        "sort": "fedavg",
        "kwargs": {}
    },
    "maxRunTime": 300,
    "realm": "default/us",
    "role": "trainer"
}